python_package/__init__.py
python_package/hello_world.py
htf_pythonprojecttest-0.0.7.dist-info/WHEEL
htf_pythonprojecttest-0.0.7.dist-info/METADATA
htf_pythonprojecttest-0.0.7.dist-info/RECORD
