Metadata-Version: 2.1
Name: HTF_PythonProjectTest
Version: 0.0.7
Summary: Sample Python Project for creating a new Python Module
Author-email: HTFWitt <kwitt@wvhtf.org>
Requires-Python: >=3.8.1
Classifier: Development Status :: 3 - Alpha
Classifier: Intended Audience :: Developers
Classifier: License :: OSI Approved :: MIT License
Classifier: Programming Language :: Python :: 3 :: Only
Classifier: Programming Language :: Python :: 3.8
Classifier: Programming Language :: Python :: 3.9
Classifier: Programming Language :: Python :: 3.10
Classifier: Programming Language :: Python :: 3.11
Requires-Dist: pyspark>=3.0.0 ; extra == "spark"
Requires-Dist: bandit[toml] ; extra == "test"
Requires-Dist: black ; extra == "test"
Requires-Dist: check-manifest ; extra == "test"
Requires-Dist: flake8-bugbear ; extra == "test"
Requires-Dist: flake8-docstrings ; extra == "test"
Requires-Dist: flake8-formatter_junit_xml ; extra == "test"
Requires-Dist: flake8 ; extra == "test"
Requires-Dist: flake8-pyproject ; extra == "test"
Requires-Dist: pre-commit ; extra == "test"
Requires-Dist: pylint ; extra == "test"
Requires-Dist: pylint_junit ; extra == "test"
Requires-Dist: pytest-cov ; extra == "test"
Requires-Dist: pytest-mock<3.11.2 ; extra == "test"
Requires-Dist: pytest-runner ; extra == "test"
Requires-Dist: pytest ; extra == "test"
Requires-Dist: pytest-github-actions-annotate-failures ; extra == "test"
Requires-Dist: shellcheck-py ; extra == "test"
Project-URL: Documentation, https://github.com/HTFWitt/PythonTemplateTest/tree/main#readme
Project-URL: Source, https://github.com/HTFWitt/PythonTemplateTest
Project-URL: Tracker, https://github.com/HTFWitt/PythonTemplateTest/issues
Provides-Extra: spark
Provides-Extra: test
